voluptuous/__init__.py
voluptuous/error.py
voluptuous/humanize.py
voluptuous/schema_builder.py
voluptuous/util.py
voluptuous/validators.py
voluptuous-0.13.0.dist-info/COPYING
voluptuous-0.13.0.dist-info/METADATA
voluptuous-0.13.0.dist-info/WHEEL
voluptuous-0.13.0.dist-info/top_level.txt
voluptuous-0.13.0.dist-info/RECORD
