Metadata-Version: 2.1
Name: voluptuous
Version: 0.13.0
Summary: UNKNOWN
Home-page: https://github.com/alecthomas/voluptuous
Download-URL: https://pypi.python.org/pypi/voluptuous
Author: Alec Thomas
Author-email: alec@swapoff.org
License: BSD
Platform: any
Classifier: Development Status :: 5 - Production/Stable
Classifier: Intended Audience :: Developers
Classifier: License :: OSI Approved :: BSD License
Classifier: Operating System :: OS Independent
Classifier: Programming Language :: Python :: 2
Classifier: Programming Language :: Python :: 2.7
Classifier: Programming Language :: Python :: 3
Classifier: Programming Language :: Python :: 3.6
Classifier: Programming Language :: Python :: 3.7
Classifier: Programming Language :: Python :: 3.8
Classifier: Programming Language :: Python :: 3.9
License-File: COPYING
